<?xml version="1.0" encoding="UTF-8"?>
<math xmlns="http://www.w3.org/1998/Math/MathML" display="block"><semantics><mrow><msub><mi>τ</mi><mi mathvariant="italic">ii</mi></msub><mrow><mrow><mo fence="true" stretchy="false">(</mo><mrow><mrow><mi>v</mi><mi>,</mi><mi>t</mi></mrow></mrow><mo fence="true" stretchy="false">)</mo></mrow><mo stretchy="false">=</mo><msub><mi>C</mi><mi mathvariant="italic">line</mi></msub></mrow><mi>ρ</mi><mrow><mo fence="true" stretchy="false">(</mo><mrow><mrow><mi>v</mi><mi>,</mi><mi>t</mi></mrow></mrow><mo fence="true" stretchy="false">)</mo></mrow><mrow><mo fence="true" stretchy="false">(</mo><mrow><mrow><msub><mi>X</mi><mi>i</mi></msub><msub><mi>f</mi><mi mathvariant="italic">ii</mi></msub></mrow></mrow><mo fence="true" stretchy="false">)</mo></mrow><mi>t</mi><msup><mi mathvariant="normal">e</mi><mrow><mrow><mo stretchy="false">−</mo><msub><mi>E</mi><mi>l</mi></msub></mrow><mo stretchy="false">/</mo><mi mathvariant="italic">kT</mi></mrow></msup></mrow><annotation encoding="StarMath 5.0">τ_{ii}(v,t) = C_{line} ρ(v,t) (X_i f_{ii}) t func e^{-E_l/kT} </annotation></semantics></math>